dobaos/__init__.py
dobaos-0.0.5.dist-info/LICENSE
dobaos-0.0.5.dist-info/METADATA
dobaos-0.0.5.dist-info/WHEEL
dobaos-0.0.5.dist-info/top_level.txt
dobaos-0.0.5.dist-info/RECORD
