Metadata-Version: 2.1
Name: dobaos
Version: 0.0.5
Summary: Python client for dobaos service.
Home-page: https://github.com/dobaos/dobaos.py
Author: Vladimir Shabunin
Author-email: va.shabunin@physics.msu.ru
License: UNKNOWN
Keywords: KNX,BAOS,dobaos,bobaos
Platform: UNKNOWN
Classifier: Development Status :: 5 - Production/Stable
Classifier: Environment :: Console
Classifier: Intended Audience :: Developers
Classifier: License :: OSI Approved :: MIT License
Classifier: Operating System :: OS Independent
Classifier: Programming Language :: Python
Classifier: Programming Language :: Python :: 3
Classifier: Programming Language :: Python :: 3.5
Classifier: Programming Language :: Python :: 3.6
Classifier: Programming Language :: Python :: 3.7
Classifier: Programming Language :: Python :: 3.8
Requires-Python: >=3.5
Requires-Dist: redis
